{"cameraMode":{"drawMode":0,"name":"Shaded","section":"Shading Mode"},"sceneLighting":true,"audioPlay":false,"sceneViewState":{"m_AlwaysRefresh":false,"showFog":true,"showSkybox":true,"showFlares":true,"showImageEffects":true,"showParticleSystems":true,"showVisualEffectGraphs":true,"m_FxEnabled":true},"in2DMode":false,"pivot":{"x":45.79144287109375,"y":11.133037567138672,"z":-111.74244689941406},"rotation":{"x":-0.1694682538509369,"y":0.5813530087471008,"z":-0.1253799945116043,"w":-0.7858849167823792},"size":23.73499298095703,"orthographic":false}